lib/__init__.py
lib/ucum.py
pyucum/__init__.py
pyucum/ucum.py
pyucum-0.1.3.dist-info/METADATA
pyucum-0.1.3.dist-info/WHEEL
pyucum-0.1.3.dist-info/top_level.txt
pyucum-0.1.3.dist-info/RECORD
