Metadata-Version: 2.1
Name: pyucum
Version: 0.1.3
Summary: Python library for using UCUM APIs to verify CDISC SDTM.LB and ADaM.ADLB
Home-page: https://github.com/stomioka/ucum
Author: Sam Tomioka
Author-email: stomioka@gmail.com
License: LICENSE
Keywords: SDTM,ADaM,LB,ADLB,UCUM
Platform: UNKNOWN
Classifier: Programming Language :: Python
Classifier: Programming Language :: Python :: 3
Classifier: Programming Language :: Python :: 3.4
Classifier: Programming Language :: Python :: 3.5
Classifier: Programming Language :: Python :: 3.6
Classifier: License :: OSI Approved :: MIT License
Classifier: Natural Language :: English
Classifier: Topic :: Scientific/Engineering
